analysis/00_gst_pytrends.py
analysis/02_dfs.py
analysis/03_visualization.py
analysis/__init__.py
analysis/dfs.py
analysis/gst_pytrends.py
analysis/gst_selenium.py
analysis/symptom_pca.py
analysis/visualization.py
data_from_gst_website/__init__.py
midterm_project_pice-0.2.0.dist-info/METADATA
midterm_project_pice-0.2.0.dist-info/WHEEL
midterm_project_pice-0.2.0.dist-info/entry_points.txt
midterm_project_pice-0.2.0.dist-info/top_level.txt
midterm_project_pice-0.2.0.dist-info/RECORD
